qt_theme_manager/__init__.py
qt_theme_manager/main.py
qt_theme_manager/cli/__init__.py
qt_theme_manager/cli/main.py
qt_theme_manager/cli/themectl.py
qt_theme_manager/config/logging_config.py
qt_theme_manager/config/theme_settings.json
qt_theme_manager/qt/__init__.py
qt_theme_manager/qt/controller.py
qt_theme_manager/qt/detection.py
qt_theme_manager/qt/loader.py
qt_theme_manager/qt/stylesheet.py
qt_theme_manager-1.0.1.dist-info/licenses/LICENSE
qt_theme_manager-1.0.1.dist-info/METADATA
qt_theme_manager-1.0.1.dist-info/WHEEL
qt_theme_manager-1.0.1.dist-info/entry_points.txt
qt_theme_manager-1.0.1.dist-info/top_level.txt
qt_theme_manager-1.0.1.dist-info/RECORD
