Metadata-Version: 2.4
Name: qt-theme-manager
Version: 1.0.1
Summary: A pure theme management library for PyQt5/PyQt6/PySide6 applications with automatic Qt framework detection
Home-page: https://github.com/scottlz0310/Qt-Theme-Manager
Author: scottlz0310
Author-email: scottlz0310 <scott.lz0310@gmail.com>
Maintainer-email: scottlz0310 <scott.lz0310@gmail.com>
License-Expression: MIT
Project-URL: Homepage, https://github.com/scottlz0310/Qt-Theme-Manager
Project-URL: Documentation, https://github.com/scottlz0310/Qt-Theme-Manager/blob/main/README.md
Project-URL: Repository, https://github.com/scottlz0310/Qt-Theme-Manager
Project-URL: Bug Tracker, https://github.com/scottlz0310/Qt-Theme-Manager/issues
Keywords: theme,qt,styling,pyside,pyqt,library,ui,desktop,theme-management,stylesheet
Classifier: Development Status :: 5 - Production/Stable
Classifier: Intended Audience :: Developers
Classifier: Operating System :: OS Independent
Classifier: Programming Language :: Python :: 3
Classifier: Programming Language :: Python :: 3.9
Classifier: Programming Language :: Python :: 3.10
Classifier: Programming Language :: Python :: 3.11
Classifier: Programming Language :: Python :: 3.12
Classifier: Topic :: Software Development :: Libraries :: Python Modules
Classifier: Topic :: Software Development :: User Interfaces
Classifier: Topic :: Desktop Environment
Classifier: Environment :: X11 Applications :: Qt
Requires-Python: >=3.9
License-File: LICENSE
Provides-Extra: pyside6
Requires-Dist: PySide6>=6.0.0; extra == "pyside6"
Provides-Extra: pyqt6
Requires-Dist: PyQt6>=6.2.0; extra == "pyqt6"
Provides-Extra: pyqt5
Requires-Dist: PyQt5>=5.15.0; extra == "pyqt5"
Provides-Extra: dev
Requires-Dist: pytest>=7.0; extra == "dev"
Requires-Dist: pytest-qt>=4.0; extra == "dev"
Requires-Dist: pytest-cov>=4.0; extra == "dev"
Requires-Dist: pytest-mock>=3.0; extra == "dev"
Requires-Dist: black>=23.0; extra == "dev"
Requires-Dist: isort>=5.12; extra == "dev"
Requires-Dist: flake8>=6.0; extra == "dev"
Requires-Dist: mypy>=1.0; extra == "dev"
Requires-Dist: autoflake>=2.0; extra == "dev"
Requires-Dist: types-setuptools; extra == "dev"
Provides-Extra: all-qt
Requires-Dist: PySide6>=6.0.0; extra == "all-qt"
Requires-Dist: PyQt6>=6.2.0; extra == "all-qt"
Requires-Dist: PyQt5>=5.15.0; extra == "all-qt"
Provides-Extra: full-dev
Requires-Dist: qt-theme-manager[dev]; extra == "full-dev"
Requires-Dist: qt-theme-manager[all-qt]; extra == "full-dev"
Requires-Dist: tox>=4.0; extra == "full-dev"
Requires-Dist: pre-commit>=3.0; extra == "full-dev"
Dynamic: author
Dynamic: home-page
Dynamic: license-file
Dynamic: requires-python
